ssbkonf/__init__.py
ssbkonf/pckg.py
ssbkonf/perturb.py
ssbkonf/suppress.py
ssbkonf/util.py
ssbkonf-0.0.10.dist-info/METADATA
ssbkonf-0.0.10.dist-info/WHEEL
ssbkonf-0.0.10.dist-info/licenses/LICENSE
ssbkonf-0.0.10.dist-info/RECORD
