Metadata-Version: 2.1
Name: ssbkonf
Version: 0.0.10
Summary: A package for disclosure control in Python, wrapping methods coded in R
Project-URL: Homepage, https://github.com/statisticsnorway/ssbkonf
Project-URL: Bug Tracker, https://github.com/statisticsnorway/ssbkonf/issues
Author-email: "Daniel P. Lupp" <dlu@ssb.com>
License-File: LICENSE
Classifier: License :: OSI Approved :: MIT License
Classifier: Operating System :: OS Independent
Classifier: Programming Language :: Python :: 3
Requires-Python: >=3.7
Requires-Dist: pandas
Requires-Dist: rpy2
